Metadata-Version: 2.1
Name: remoteit
Version: 0.0.1
Summary: Wrap functions to run in separate threads/processes.
Home-page: https://github.com/beasteers/remoteit
Author: Bea Steers
Author-email: bea.steers@gmail.com
License: MIT License
Platform: UNKNOWN
